{
  "brandName": "Capitalta",
  "title": "Soluciones Financieras",
  "company": {
    "name": "Capitalta",
    "url": "https://capitalta.com.mx",
    "socialLink": {
      "linkedin": "#",
      "instagram": "#",
      "facebook": "#",
      "youtube": "#",
      "github": "#",
      "dribble": "#",
      "discord": "#",
      "support": "#"
    }
  },
  "logo": {
    "main": "/assets/images/capitalta/logo-1.jpeg",
    "logoIcon": "/assets/images/capitalta/logo-1.jpeg",
    "logoFab": "",
    "logoWatermark": ""
  }
}
